MANIFEST.in
README.md
setup.py
iampq/__init__.py
iampq/__version__.py
iampq/base.py
iampq/conf.py
iampq/conn.py
iampq/entities.py
iampq/messaging.py
iampq/serializer.py
iampq/test.py
iampq/toro_test.py
iampq/utils.py
iampq.egg-info/PKG-INFO
iampq.egg-info/SOURCES.txt
iampq.egg-info/dependency_links.txt
iampq.egg-info/not-zip-safe
iampq.egg-info/requires.txt
iampq.egg-info/top_level.txt
iampq/tests/__init__.py
iampq/tests/spider.py
iampq/tests/toro_test.py