Metadata-Version: 1.1
Name: iampq
Version: 0.0.dev4
Summary: A non-blocking thin pika wrapper that adapts logic of kombu.
Home-page: https://bitbucket.org/Rustem/iampq
Author: Rustem Kamun
Author-email: r.kamun@gmail.com
License: MIT
Keywords: amqp rabbitmq pika tornado
Platform: UNKNOWN
Classifier: Development Status :: 5 - Production/Stable
Classifier: Intended Audience :: Developers
Classifier: License :: OSI Approved :: MIT License
Classifier: Topic :: Software Development :: Build Tools
Classifier: Programming Language :: Python :: 2.7
Classifier: Programming Language :: Python :: 3
Classifier: Programming Language :: Python :: 3.1
Classifier: Programming Language :: Python :: 3.2
